HISTORY.rst
LICENSE
MANIFEST.in
README.rst
full-requirements.txt
setup.cfg
setup.py
hachi/__init__.py
hachi/compat.py
hachi/const.py
hachi/core.py
hachi/exceptions.py
hachi/request.py
hachi/response.py
hachi/serial.py
hachi/tests.py
hachi/twisted.py
hachi.egg-info/PKG-INFO
hachi.egg-info/SOURCES.txt
hachi.egg-info/dependency_links.txt
hachi.egg-info/requires.txt
hachi.egg-info/top_level.txt