Metadata-Version: 1.1
Name: hachi
Version: 0.5
Summary: XBee API
Home-page: https://github.com/Diaoul/hachi
Author: Antoine Bertin
Author-email: diaoulael@gmail.com
License: Copyright 2013 Antoine Bertin
